SunNeurons/Fill.py
SunNeurons/SunNeurons.py
SunNeurons/__init__.py
SunNeurons-0.0.3.dist-info/METADATA
SunNeurons-0.0.3.dist-info/WHEEL
SunNeurons-0.0.3.dist-info/top_level.txt
SunNeurons-0.0.3.dist-info/RECORD
