Metadata-Version: 2.1
Name: SunNeurons
Version: 0.0.3
Summary: SunNeurons
Home-page: UNKNOWN
Author: Sunny Kumar
Author-email: <1709krsunny@gmail.com>
License: UNKNOWN
Keywords: python,neural networks,ann,mcculloh-pitt,ART neural network
Platform: UNKNOWN
Classifier: Development Status :: 1 - Planning
Classifier: Intended Audience :: Developers
Classifier: Programming Language :: Python :: 3
Classifier: Operating System :: Unix
Classifier: Operating System :: MacOS :: MacOS X
Classifier: Operating System :: Microsoft :: Windows
Requires-Dist: numpy
Requires-Dist: matplotlib
Requires-Dist: scikit-learn
Requires-Dist: tensorflow
